ompl/__init__.py
ompl/_omplpy.cpython-37m-x86_64-linux-gnu.so
ompl/py.typed
ompl/include/ompl-1.6/ompl/config.h
ompl/include/ompl-1.6/ompl/base/ConstrainedSpaceInformation.h
ompl/include/ompl-1.6/ompl/base/Constraint.h
ompl/include/ompl-1.6/ompl/base/Cost.h
ompl/include/ompl-1.6/ompl/base/DiscreteMotionValidator.h
ompl/include/ompl-1.6/ompl/base/GenericParam.h
ompl/include/ompl-1.6/ompl/base/Goal.h
ompl/include/ompl-1.6/ompl/base/GoalTypes.h
ompl/include/ompl-1.6/ompl/base/MotionValidator.h
ompl/include/ompl-1.6/ompl/base/OptimizationObjective.h
ompl/include/ompl-1.6/ompl/base/Path.h
ompl/include/ompl-1.6/ompl/base/Planner.h
ompl/include/ompl-1.6/ompl/base/PlannerData.h
ompl/include/ompl-1.6/ompl/base/PlannerDataGraph.h
ompl/include/ompl-1.6/ompl/base/PlannerDataStorage.h
ompl/include/ompl-1.6/ompl/base/PlannerStatus.h
ompl/include/ompl-1.6/ompl/base/PlannerTerminationCondition.h
ompl/include/ompl-1.6/ompl/base/PrecomputedStateSampler.h
ompl/include/ompl-1.6/ompl/base/ProblemDefinition.h
ompl/include/ompl-1.6/ompl/base/ProjectionEvaluator.h
ompl/include/ompl-1.6/ompl/base/ScopedState.h
ompl/include/ompl-1.6/ompl/base/SolutionNonExistenceProof.h
ompl/include/ompl-1.6/ompl/base/SpaceInformation.h
ompl/include/ompl-1.6/ompl/base/State.h
ompl/include/ompl-1.6/ompl/base/StateSampler.h
ompl/include/ompl-1.6/ompl/base/StateSamplerArray.h
ompl/include/ompl-1.6/ompl/base/StateSpace.h
ompl/include/ompl-1.6/ompl/base/StateSpaceTypes.h
ompl/include/ompl-1.6/ompl/base/StateStorage.h
ompl/include/ompl-1.6/ompl/base/StateValidityChecker.h
ompl/include/ompl-1.6/ompl/base/TypedSpaceInformation.h
ompl/include/ompl-1.6/ompl/base/TypedStateValidityChecker.h
ompl/include/ompl-1.6/ompl/base/ValidStateSampler.h
ompl/include/ompl-1.6/ompl/base/goals/GoalLazySamples.h
ompl/include/ompl-1.6/ompl/base/goals/GoalRegion.h
ompl/include/ompl-1.6/ompl/base/goals/GoalSampleableRegion.h
ompl/include/ompl-1.6/ompl/base/goals/GoalSpace.h
ompl/include/ompl-1.6/ompl/base/goals/GoalState.h
ompl_thin-0.0.18.dist-info/LICENSE.md
ompl_thin-0.0.18.dist-info/METADATA
ompl_thin-0.0.18.dist-info/WHEEL
ompl_thin-0.0.18.dist-info/top_level.txt
ompl_thin-0.0.18.dist-info/RECORD
