Metadata-Version: 2.1
Name: ompl-thin
Version: 0.0.18
Summary: thin ompl python wrapper
Home-page: UNKNOWN
Author: Hirokazu Ishida
Author-email: UNKNOWN
License: MIT
Platform: UNKNOWN
Requires-Dist: numpy
